{
    "oil_id": "AD03131",
    "adios_data_model_version": "0.11.0",
    "metadata": {
        "name": "GINA KROG CRUDE (2018)",
        "source_id": "AD03131",
        "location": "NORWAY",
        "reference": {
            "year": 2018,
            "reference": "Chever F., 2018, Weathering and dispersibility study of the GINA KROG crude oil at the laboratory and pilot scale in simulated local conditions, Equinor Final Report"
        },
        "product_type": "Crude Oil NOS",
        "model_completeness": 48,
        "gnome_suitable": true
    },
    "sub_samples": [
        {
            "metadata": {
                "name": "Fresh Oil Sample",
                "short_name": "Fresh Oil",
                "fraction_evaporated": {
                    "value": 0.0,
                    "unit": "fraction",
                    "unit_type": "massfraction"
                }
            },
            "physical_properties": {
                "pour_point": {
                    "measurement": {
                        "unit": "K",
                        "min_value": 279.0,
                        "max_value": 297.0,
                        "unit_type": "temperature"
                    }
                },
                "flash_point": {
                    "measurement": {
                        "unit": "K",
                        "max_value": 373.0,
                        "unit_type": "temperature"
                    }
                },
                "densities": [
                    {
                        "density": {
                            "value": 879.0,
                            "unit": "kg/m^3",
                            "unit_type": "density"
                        },
                        "ref_temp": {
                            "value": 278.0,
                            "unit": "K",
                            "unit_type": "temperature"
                        }
                    }
                ],
                "dynamic_viscosities": [
                    {
                        "viscosity": {
                            "value": 0.109,
                            "unit": "kg/(m s)",
                            "unit_type": "dynamicviscosity"
                        },
                        "ref_temp": {
                            "value": 278.0,
                            "unit": "K",
                            "unit_type": "temperature"
                        }
                    }
                ]
            },
            "SARA": {
                "asphaltenes": {
                    "value": 0.0031,
                    "unit": "fraction",
                    "unit_type": "massfraction"
                }
            },
            "distillation_data": {
                "type": "volume fraction",
                "cuts": [
                    {
                        "fraction": {
                            "value": 0.04,
                            "unit": "fraction",
                            "unit_type": "volumefraction"
                        },
                        "vapor_temp": {
                            "value": 30.850000000000023,
                            "unit": "C",
                            "unit_type": "temperature"
                        }
                    },
                    {
                        "fraction": {
                            "value": 0.044,
                            "unit": "fraction",
                            "unit_type": "volumefraction"
                        },
                        "vapor_temp": {
                            "value": 50.85000000000002,
                            "unit": "C",
                            "unit_type": "temperature"
                        }
                    },
                    {
                        "fraction": {
                            "value": 0.092,
                            "unit": "fraction",
                            "unit_type": "volumefraction"
                        },
                        "vapor_temp": {
                            "value": 104.85000000000002,
                            "unit": "C",
                            "unit_type": "temperature"
                        }
                    },
                    {
                        "fraction": {
                            "value": 0.249,
                            "unit": "fraction",
                            "unit_type": "volumefraction"
                        },
                        "vapor_temp": {
                            "value": 199.85000000000002,
                            "unit": "C",
                            "unit_type": "temperature"
                        }
                    },
                    {
                        "fraction": {
                            "value": 0.428,
                            "unit": "fraction",
                            "unit_type": "volumefraction"
                        },
                        "vapor_temp": {
                            "value": 299.85,
                            "unit": "C",
                            "unit_type": "temperature"
                        }
                    },
                    {
                        "fraction": {
                            "value": 0.797,
                            "unit": "fraction",
                            "unit_type": "volumefraction"
                        },
                        "vapor_temp": {
                            "value": 499.85,
                            "unit": "C",
                            "unit_type": "temperature"
                        }
                    }
                ]
            },
            "bulk_composition": [
                {
                    "name": "wax_content",
                    "measurement": {
                        "value": 0.065,
                        "unit": "fraction",
                        "unit_type": "massfraction"
                    }
                }
            ]
        },
        {
            "metadata": {
                "name": "73.1% Evaporated",
                "short_name": "73.1% Evaporated",
                "fraction_evaporated": {
                    "value": 0.731,
                    "unit": "fraction",
                    "unit_type": "massfraction"
                }
            },
            "physical_properties": {
                "dynamic_viscosities": [
                    {
                        "viscosity": {
                            "value": 12.946,
                            "unit": "kg/(m s)",
                            "unit_type": "dynamicviscosity"
                        },
                        "ref_temp": {
                            "value": 278.0,
                            "unit": "K",
                            "unit_type": "temperature"
                        }
                    }
                ]
            }
        },
        {
            "metadata": {
                "name": "73.7% Evaporated",
                "short_name": "73.7% Evaporated",
                "fraction_evaporated": {
                    "value": 0.737,
                    "unit": "fraction",
                    "unit_type": "massfraction"
                }
            },
            "physical_properties": {
                "densities": [
                    {
                        "density": {
                            "value": 966.0,
                            "unit": "kg/m^3",
                            "unit_type": "density"
                        },
                        "ref_temp": {
                            "value": 278.0,
                            "unit": "K",
                            "unit_type": "temperature"
                        }
                    }
                ]
            }
        },
        {
            "metadata": {
                "name": "78.3% Evaporated",
                "short_name": "78.3% Evaporated",
                "fraction_evaporated": {
                    "value": 0.783,
                    "unit": "fraction",
                    "unit_type": "massfraction"
                }
            },
            "physical_properties": {
                "dynamic_viscosities": [
                    {
                        "viscosity": {
                            "value": 6.938,
                            "unit": "kg/(m s)",
                            "unit_type": "dynamicviscosity"
                        },
                        "ref_temp": {
                            "value": 278.0,
                            "unit": "K",
                            "unit_type": "temperature"
                        }
                    }
                ]
            }
        },
        {
            "metadata": {
                "name": "85.0% Evaporated",
                "short_name": "85.0% Evaporated",
                "fraction_evaporated": {
                    "value": 0.85,
                    "unit": "fraction",
                    "unit_type": "massfraction"
                }
            },
            "physical_properties": {
                "densities": [
                    {
                        "density": {
                            "value": 903.0,
                            "unit": "kg/m^3",
                            "unit_type": "density"
                        },
                        "ref_temp": {
                            "value": 278.0,
                            "unit": "K",
                            "unit_type": "temperature"
                        }
                    }
                ]
            }
        },
        {
            "metadata": {
                "name": "86.0% Evaporated",
                "short_name": "86.0% Evaporated",
                "fraction_evaporated": {
                    "value": 0.86,
                    "unit": "fraction",
                    "unit_type": "massfraction"
                }
            },
            "physical_properties": {
                "densities": [
                    {
                        "density": {
                            "value": 893.0,
                            "unit": "kg/m^3",
                            "unit_type": "density"
                        },
                        "ref_temp": {
                            "value": 278.0,
                            "unit": "K",
                            "unit_type": "temperature"
                        }
                    }
                ],
                "dynamic_viscosities": [
                    {
                        "viscosity": {
                            "value": 0.35,
                            "unit": "kg/(m s)",
                            "unit_type": "dynamicviscosity"
                        },
                        "ref_temp": {
                            "value": 278.0,
                            "unit": "K",
                            "unit_type": "temperature"
                        }
                    }
                ]
            }
        }
    ],
    "status": [
        "E030: Oils must have an API",
        "W009: Distillation fraction recovered is missing or invalid",
        "W010: Temperature: 279.00 K (5.85 C) is close to 6.00 C -- looks like it could be a K to C conversion error",
        "W010: Temperature: 297.00 K (23.85 C) is close to 24.00 C -- looks like it could be a K to C conversion error",
        "W010: Temperature: 373.00 K (99.85 C) is close to 100.00 C -- looks like it could be a K to C conversion error"
    ],
    "review_status": {
        "status": "Not Reviewed"
    }
}